setup.py
config/__init__.py
data/__init__.py
data/variables.py
log_configs/__init__.py
log_configs/base_logger.py
log_configs/client_log_config.py
log_configs/server_log_config.py
logs/__init__.py
server/__init__.py
server/add_user.py
server/config_window.py
server/core.py
server/main_window.py
server/remove_user.py
server/server_database.py
server/stat_window.py
server_project.egg-info/PKG-INFO
server_project.egg-info/SOURCES.txt
server_project.egg-info/dependency_links.txt
server_project.egg-info/requires.txt
server_project.egg-info/top_level.txt
unit_tests/__init__.py
unit_tests/test_client.py
unit_tests/test_server.py