Metadata-Version: 1.0
Name: server-project
Version: 0.0.1
Summary: mess_server_proj
Home-page: UNKNOWN
Author: FidelSol
Author-email: fsoloviov2020@mail.ru
License: UNKNOWN
Platform: UNKNOWN
